git_conflict.py
gitconflict-0.1.dist-info/top_level.txt
gitconflict-0.1.dist-info/RECORD
gitconflict-0.1.dist-info/WHEEL
gitconflict-0.1.dist-info/METADATA
gitconflict-0.1.dist-info/DESCRIPTION.rst
gitconflict-0.1.dist-info/metadata.json
gitconflict-0.1.dist-info/entry_points.txt
