Metadata-Version: 2.0
Name: gitconflict
Version: 0.1
Summary: Git merge-conflicts checker
Home-page: https://github.com/einmalfel/git-aflow
Author: Vasily Makarov
Author-email: einmalfel@gmail.com
License: GNU LGPL 2.1
Keywords: git merge conflict detector git-aflow
Platform: UNKNOWN
Classifier: Development Status :: 2 - Pre-Alpha
Classifier: Environment :: Console
Classifier: Operating System :: POSIX :: Linux
Classifier: Programming Language :: Python :: 3 :: Only
Classifier: Programming Language :: Python :: 3.2
Classifier: Topic :: Software Development :: Version Control
Classifier: License :: OSI Approved :: GNU Lesser General Public License v2 or later (LGPLv2+)
Provides: gitconflict
Requires-Dist: thingitwrapper
